setup.py
experiments/__init__.py
experiments/abridge.py
experiments/atod.py
experiments/bug.py
experiments/buzzer.py
experiments/buzzer2.py
experiments/i2cdesc.py
experiments/morsecode.py
experiments/pair_client.py
experiments/pair_server.py
experiments/pibio.py
experiments/psenvpub.py
experiments/psenvsub.py
experiments/psenvsub2.py
experiments/pwm.py
experiments/servo.py
experiments/servo2.py
experiments/servo3.py
experiments/sonar_trigger_echo.py
experiments/zmq_exc.py
experiments/xideco_tweeter/__init__.py
experiments/xideco_tweeter/xihbt.py
experiments/xideco_tweeter/xitwitter_bridge.py
xideco/__init__.py
xideco.egg-info/PKG-INFO
xideco.egg-info/SOURCES.txt
xideco.egg-info/dependency_links.txt
xideco.egg-info/entry_points.txt
xideco.egg-info/requires.txt
xideco.egg-info/top_level.txt
xideco/arduino_bridge/__init__.py
xideco/arduino_bridge/xiab.py
xideco/beaglebone_bridge/__init__.py
xideco/beaglebone_bridge/xibb.py
xideco/beaglebone_bridge/xibbi2c.py
xideco/data_files/__init__.py
xideco/data_files/configuration/__init__.py
xideco/data_files/configuration/configuration.cfg
xideco/data_files/port_map/__init__.py
xideco/data_files/port_map/port_map.py
xideco/data_files/scratch_files/__init__.py
xideco/data_files/scratch_files/extensions/__init__.py
xideco/data_files/scratch_files/extensions/m_s2aio.s2e
xideco/data_files/scratch_files/extensions/m_s2aio_DE.s2e
xideco/data_files/scratch_files/extensions/m_s2aio_ES.s2e
xideco/data_files/scratch_files/extensions/m_s2aio_FR.s2e
xideco/data_files/scratch_files/extensions/m_s2aio_GR.s2e
xideco/data_files/scratch_files/extensions/m_s2aio_IT.s2e
xideco/data_files/scratch_files/extensions/m_s2aio_KO.s2e
xideco/data_files/scratch_files/extensions/m_s2aio_NL.s2e
xideco/data_files/scratch_files/extensions/m_s2aio_PT.s2e
xideco/data_files/scratch_files/extensions/m_s2aio_zh_CN.s2e
xideco/data_files/scratch_files/extensions/m_s2aio_zh_TW.s2e
xideco/data_files/scratch_files/projects/__init__.py
xideco/data_files/scratch_files/projects/m_s2aio.sb2
xideco/data_files/scratch_files/projects/m_s2aio_DE.sb2
xideco/data_files/scratch_files/projects/m_s2aio_ES.sb2
