Metadata-Version: 1.1
Name: xideco
Version: 0.5.2
Summary: A Network Enabled Software Backplane
Home-page: https://github.com/MrYsLab/xideco/wiki
Author: Alan Yorinks
Author-email: MisterYsLab@gmail.com
License: GNU General Public License v3 (GPLv3)
Keywords: Firmata,Arduino,Scratch,ZeroMQ
Platform: UNKNOWN
Classifier: Development Status :: 4 - Beta
Classifier: Environment :: Other Environment
Classifier: Intended Audience :: Education
Classifier: License :: OSI Approved :: GNU General Public License v3 or later (GPLv3+)
Classifier: Operating System :: OS Independent
Classifier: Programming Language :: Python :: 3.5
Classifier: Topic :: Education
Classifier: Topic :: Software Development
Classifier: Topic :: Home Automation
Classifier: Topic :: System :: Hardware
